jps_llm_prompt_app/__init__.py
jps_llm_prompt_app/constants.py
jps_llm_prompt_app/prompt_cli.py
jps_llm_prompt_app-0.1.0.dist-info/licenses/LICENSE
jps_llm_prompt_app-0.1.0.dist-info/METADATA
jps_llm_prompt_app-0.1.0.dist-info/WHEEL
jps_llm_prompt_app-0.1.0.dist-info/entry_points.txt
jps_llm_prompt_app-0.1.0.dist-info/top_level.txt
jps_llm_prompt_app-0.1.0.dist-info/RECORD
