Metadata-Version: 2.4
Name: jps-llm-prompt-app
Version: 0.1.0
Summary: Lightweight app for selecting prompts to submit to LLMs
Author-email: Jaideep Sundaram <jai.python3@gmail.com>
License: MIT
Project-URL: Homepage, https://github.com/jai-python3/jps-llm-prompt-app
Project-URL: Repository, https://github.com/jai-python3/jps-llm-prompt-app
Project-URL: Issues, https://github.com/jai-python3/jps-llm-prompt-app/issues
Keywords: cookiecutter,bootstrap,project-generator,automation
Classifier: Programming Language :: Python :: 3
Classifier: License :: OSI Approved :: MIT License
Classifier: Operating System :: OS Independent
Requires-Python: >=3.10
License-File: LICENSE
Requires-Dist: typer>=0.12.3
Requires-Dist: click==8.3.1
Requires-Dist: markdown-it-py==4.0.0
Requires-Dist: mdurl==0.1.2
Requires-Dist: prompt_toolkit==3.0.52
Requires-Dist: Pygments==2.19.2
Requires-Dist: pyperclip==1.11.0
Requires-Dist: PyYAML==6.0.3
Requires-Dist: rich==14.2.0
Requires-Dist: shellingham==1.5.4
Requires-Dist: typer==0.20.0
Requires-Dist: typing_extensions==4.15.0
Requires-Dist: wcwidth==0.2.14
Provides-Extra: dev
Requires-Dist: flake8>=7.0.0; extra == "dev"
Requires-Dist: black>=24.0.0; extra == "dev"
Requires-Dist: build>=1.2.1; extra == "dev"
Requires-Dist: twine>=5.0.0; extra == "dev"
Requires-Dist: pytest>=8.0.0; extra == "dev"
Requires-Dist: pytest-cov>=5.0.0; extra == "dev"
Requires-Dist: isort>=5.13.0; extra == "dev"
Requires-Dist: codecov>=2.1.13; extra == "dev"
Requires-Dist: autoflake>=2.3.1; extra == "dev"
Requires-Dist: pre-commit>=3.8.0; extra == "dev"
Requires-Dist: bandit>=1.7.9; extra == "dev"
Requires-Dist: vulture>=2.11; extra == "dev"
Requires-Dist: flynt>=1.0.1; extra == "dev"
Requires-Dist: pydocstyle>=6.3.0; extra == "dev"
Requires-Dist: darglint>=1.8.1; extra == "dev"
Requires-Dist: mypy>=1.12.1; extra == "dev"
Requires-Dist: bump-my-version>=1.0.1; extra == "dev"
Requires-Dist: git-changelog>=2.7.0; extra == "dev"
Dynamic: license-file
